attach.me-0.1.1.dist-info/LICENSE.txt
attach.me-0.1.1.dist-info/METADATA
attach.me-0.1.1.dist-info/RECORD
attach.me-0.1.1.dist-info/WHEEL
attach.me-0.1.1.dist-info/top_level.txt
attachme/__init__.py
